HISTORY.rst
LICENSE.rst
MANIFEST.in
README.rst
setup.py
src/collective/__init__.py
src/collective/__init__.pyo
src/collective.js.jquerygantt.egg-info/PKG-INFO
src/collective.js.jquerygantt.egg-info/SOURCES.txt
src/collective.js.jquerygantt.egg-info/dependency_links.txt
src/collective.js.jquerygantt.egg-info/entry_points.txt
src/collective.js.jquerygantt.egg-info/namespace_packages.txt
src/collective.js.jquerygantt.egg-info/requires.txt
src/collective.js.jquerygantt.egg-info/top_level.txt
src/collective.js.jquerygantt.egg-info/zip-safe
src/collective/js/__init__.py
src/collective/js/jquerygantt/__init__.py
src/collective/js/jquerygantt/configure.zcml
src/collective/js/jquerygantt/example.pt
src/collective/js/jquerygantt/example.py
src/collective/js/jquerygantt/profiles/default/cssregistry.xml
src/collective/js/jquerygantt/profiles/default/jsregistry.xml
src/collective/js/jquerygantt/profiles/default/metadata.xml
src/collective/js/jquerygantt/resources/.gitignore
src/collective/js/jquerygantt/resources/CONTRIBUTORS.md
src/collective/js/jquerygantt/resources/README.md
src/collective/js/jquerygantt/resources/index.html
src/collective/js/jquerygantt/resources/css/style.css
src/collective/js/jquerygantt/resources/img/.DS_Store
src/collective/js/jquerygantt/resources/img/grid.png
src/collective/js/jquerygantt/resources/img/icon_sprite.png
src/collective/js/jquerygantt/resources/img/loader_bg.png
src/collective/js/jquerygantt/resources/img/slider_handle.png
src/collective/js/jquerygantt/resources/js/dataDays.js
src/collective/js/jquerygantt/resources/js/dataDaysEnh.js
src/collective/js/jquerygantt/resources/js/dataHours.js
src/collective/js/jquerygantt/resources/js/jquery-1.7.min.js
src/collective/js/jquerygantt/resources/js/jquery.cookie.js
src/collective/js/jquerygantt/resources/js/jquery.fn.gantt.js
src/collective/js/jquerygantt/resources/js/jquery.fn.gantt.min.js
src/collective/monkeypatcher/__init__.py
src/collective/monkeypatcher/interfaces.py
src/collective/monkeypatcher/meta.py
src/collective/monkeypatcher/tests/__init__.py
src/collective/monkeypatcher/tests/common.py
src/collective/monkeypatcher/tests/dummypatch.py
src/collective/monkeypatcher/tests/test_monkeypatcher.py
src/collective/z3cform/__init__.py
src/collective/z3cform/datetimewidget/__init__.py
src/collective/z3cform/datetimewidget/converter.py
src/collective/z3cform/datetimewidget/i18n.py
